chain/__init__.py
chain/prompt.py
clients/__init__.py
clients/singulr_ingestion_client.py
clients/tests/__init__.py
env/__init__.py
env/environment.py
library/__init__.py
library/langchain/__init__.py
library/langchain/env.py
library/langsmith/__init__.py
library/langsmith/utils.py
llm/__init__.py
llm/llm_invocation_params.py
llm/llm_stats.py
mapper/__init__.py
mapper/env_generator.py
mapper/span_generator.py
payload/__init__.py
payload/ingestion_payload.py
span/__init__.py
span/content.py
span/primitive_attribute.py
span/result.py
span/span.py
trace/__init__.py
trace/trace.py
trace_tree/__init__.py
trace_tree/singulr_trace_tree.py
singulr-1.0.0.dist-info/METADATA
singulr-1.0.0.dist-info/WHEEL
singulr-1.0.0.dist-info/top_level.txt
singulr-1.0.0.dist-info/RECORD
